insightful/__init__.py
insightful/accessConfluence.py
insightful/cli.py
insightful/connection.py
insightful/main.py
insightful/settings.py
insightful-0.2.dist-info/LICENCE.txt
insightful-0.2.dist-info/METADATA
insightful-0.2.dist-info/WHEEL
insightful-0.2.dist-info/entry_points.txt
insightful-0.2.dist-info/top_level.txt
insightful-0.2.dist-info/RECORD
