Metadata-Version: 2.1
Name: insightful
Version: 0.2
Summary: UNKNOWN
Home-page: UNKNOWN
Author: Adnan Hoq
Author-email: ahoqabir@gmail.com
License: MIT
Platform: UNKNOWN
Requires-Dist: beautifulsoup4 (==4.9.1)
Requires-Dist: bs4 (==0.0.1)
Requires-Dist: click (==7.1.2)
Requires-Dist: lxml (==4.5.2)
Requires-Dist: Markdown (==3.2.2)
Requires-Dist: mysql-connector-python (==8.0.21)
Requires-Dist: protobuf (==3.13.0)
Requires-Dist: python-docx (==0.8.10)
Requires-Dist: six (==1.11.0)
Requires-Dist: soupsieve (==2.0.1)
Requires-Dist: SQLAlchemy (==1.3.19)
Requires-Dist: requests (==2.20.1)
Requires-Dist: html2markdown (==0.1.7)
